setup.py
brynq_sdk_monday/__init__.py
brynq_sdk_monday/extract_monday.py
brynq_sdk_monday/extract_tracket.py
brynq_sdk_monday/upload_tracket.py
brynq_sdk_monday.egg-info/PKG-INFO
brynq_sdk_monday.egg-info/SOURCES.txt
brynq_sdk_monday.egg-info/dependency_links.txt
brynq_sdk_monday.egg-info/not-zip-safe
brynq_sdk_monday.egg-info/requires.txt
brynq_sdk_monday.egg-info/top_level.txt