Metadata-Version: 1.0
Name: brynq-sdk-monday
Version: 1.2.4
Summary: Monday.com wrapper from BrynQ
Home-page: UNKNOWN
Author: BrynQ
Author-email: support@brynq.com
License: BrynQ License
Platform: UNKNOWN
